unitedenergy/__init__.py
unitedenergy/periodoffset.py
unitedenergy/reportperiod.py
unitedenergy/unitedenergy.py
unitedenergy/unitedenergyerror.py
unitedenergy_usage_data-0.0.1.dist-info/LICENSE
unitedenergy_usage_data-0.0.1.dist-info/METADATA
unitedenergy_usage_data-0.0.1.dist-info/WHEEL
unitedenergy_usage_data-0.0.1.dist-info/top_level.txt
unitedenergy_usage_data-0.0.1.dist-info/RECORD
